flexi_splitter/__init__.py
flexi_splitter/flexi_splitter.py
flexi_splitter/suffix_tree.py
rmi_splitter/__init__.py
rmi_splitter/rmi_splitter.py
rmi_splitter/suffix_tree.py
flexi_splitter-1.0.2.dist-info/METADATA
flexi_splitter-1.0.2.dist-info/WHEEL
flexi_splitter-1.0.2.dist-info/entry_points.txt
flexi_splitter-1.0.2.dist-info/top_level.txt
flexi_splitter-1.0.2.dist-info/RECORD
